{
  "url": "https://dtu.ac.in/",
  "professors": [
    {
      "name": "Head of Department",
      "email": "dkumar@dce.ac.in",
      "phone": ""
    },
    {
      "name": "Prof. Anil Kumar",
      "email": "asl213@gmail.com",
      "phone": ""
    },
    {
      "name": "Prof. S. G. Warkar",
      "email": "sudhirwarkar@gmail.com",
      "phone": ""
    },
    {
      "name": "Prof. R. C. Sharma",
      "email": "rchsharma@dce.ac.in",
      "phone": ""
    },
    {
      "name": "Prof. Archna   Rani",
      "email": "archanarani@dce.ac.in",
      "phone": ""
    },
    {
      "name": "Prof. Ram Singh",
      "email": "singh_dr_ram@yahoo.com",
      "phone": ""
    },
    {
      "name": "Prof. Roli Purwar",
      "email": "roli.purwar@gmail.com",
      "phone": ""
    },
    {
      "name": "rkg67ap",
      "email": "rkg67ap@yahoo.com",
      "phone": ""
    },
    {
      "name": "anil.kumar",
      "email": "anil.kumar@cy.iitr.ac.in",
      "phone": ""
    },
    {
      "name": "anubhamandal",
      "email": "anubhamandal@dce.ac.in",
      "phone": ""
    },
    {
      "name": "Dr. Richa Srivastava",
      "email": "sri_richa@rediffmail.com",
      "phone": ""
    },
    {
      "name": "Dr. D Santhiya",
      "email": "deenan.santhiya@gmail.com",
      "phone": ""
    },
    {
      "name": "Dr. Raminder Kaur",
      "email": "raminderkaur@dce.ac.in",
      "phone": ""
    },
    {
      "name": "Dr. Saurabh Mehta",
      "email": "saurabh.dtu@gmail.com",
      "phone": ""
    },
    {
      "name": "Dr. Poonam Singh",
      "email": "poonam@dtu.ac.in",
      "phone": ""
    },
    {
      "name": "Dr. Manish Jain",
      "email": "manishjain@dtu.ac.in",
      "phone": ""
    },
    {
      "name": "Dr. Jay Singh",
      "email": "jaysingh@dtu.ac.in",
      "phone": ""
    },
    {
      "name": "Dr. Chandra Mouli Pandey",
      "email": "cmp.npl@gmail.com",
      "phone": ""
    },
    {
      "name": "Head of Department",
      "email": "rsrivastava@dce.ac.in",
      "phone": ""
    },
    {
      "name": "Associate Head of Department",
      "email": "cpsphd@rediffmail.com",
      "phone": ""
    },
    {
      "name": "Professor",
      "email": "Sangita_kansal15@rediffmail.com",
      "phone": ""
    },
    {
      "name": "spkumar",
      "email": "spkumar@dce.ac.in",
      "phone": ""
    },
    {
      "name": "dr_naokant_deo",
      "email": "dr_naokant_deo@yahoo.com",
      "phone": ""
    },
    {
      "name": "anjanagupta",
      "email": "anjanagupta@dce.ac.in",
      "phone": ""
    },
    {
      "name": "lndas",
      "email": "lndas@dce.ac.in",
      "phone": ""
    },
    {
      "name": "vpkaushik",
      "email": "vpkaushik@kuk.ac.in",
      "phone": ""
    },
    {
      "name": "apkaushik",
      "email": "apkaushik@gmail.com",
      "phone": ""
    },
    {
      "name": "Prof. H.C. Taneja",
      "email": "hctaneja@rediffmail.com",
      "phone": ""
    },
    {
      "name": "Prof. H.C. Taneja",
      "email": "hctaneja@dce.ac.in",
      "phone": ""
    },
    {
      "name": "brijkishore.tyagi",
      "email": "brijkishore.tyagi@gmail.com",
      "phone": ""
    },
    {
      "name": "Associate Professor",
      "email": "Vivekkumar.ag@gmail.com",
      "phone": ""
    },
    {
      "name": "Rathi.nilam",
      "email": "Rathi.nilam@gmail.com",
      "phone": ""
    },
    {
      "name": "Assistant Professor",
      "email": "sukuyd@gmail.com",
      "phone": ""
    },
    {
      "name": "goonjanjain",
      "email": "goonjanjain@dtu.ac.in",
      "phone": ""
    },
    {
      "name": "dineshudar",
      "email": "dineshudar@dtu.ac.in",
      "phone": ""
    },
    {
      "name": "satyabrata",
      "email": "satyabrata@dtu.ac.in",
      "phone": ""
    },
    {
      "name": "anshularora",
      "email": "anshularora@dtu.ac.in",
      "phone": ""
    },
    {
      "name": "rohitkumar",
      "email": "rohitkumar@dtu.ac.in",
      "phone": ""
    },
    {
      "name": "trashagupta",
      "email": "trashagupta@gmail.com",
      "phone": ""
    },
    {
      "name": "sumedhaseniaray",
      "email": "sumedhaseniaray@dtu.ac.in",
      "phone": ""
    },
    {
      "name": "jamkhongamtouthang",
      "email": "jamkhongamtouthang@dtu.ac.in",
      "phone": ""
    },
    {
      "name": "Prof. Vinod Singh",
      "email": "vinodsingh@dtu.ac.in",
      "phone": ""
    },
    {
      "name": "suresh321sharma",
      "email": "suresh321sharma@gmail.com",
      "phone": ""
    },
    {
      "name": "prof_sureshsharma",
      "email": "prof_sureshsharma@dtu.ac.in",
      "phone": ""
    },
    {
      "name": "rinkusharmagtbit",
      "email": "rinkusharmagtbit@gmail.com",
      "phone": ""
    },
    {
      "name": "Dr. Nitin K. Puri",
      "email": "nitinkumarpuri@dtu.ac.in",
      "phone": ""
    },
    {
      "name": "Dr. Nitin K. Puri",
      "email": "nitinpuri2002@yahoo.co.in",
      "phone": ""
    },
    {
      "name": "Dr. Rishu Chaujar",
      "email": "rishuchaujar@rediffmail.com",
      "phone": ""
    },
    {
      "name": "Dr. Yogita Kalra",
      "email": "dryogitakalra@gmail.com",
      "phone": ""
    },
    {
      "name": "Dr. Mohan S. Mehata",
      "email": "msmehata@dtu.ac.in",
      "phone": ""
    },
    {
      "name": "Dr. Pawan Tyagi",
      "email": "tyagi_pawan@yahoo.co.in",
      "phone": ""
    },
    {
      "name": "Dr. Ajeet Kumar",
      "email": "ajeetdph@gmail.com",
      "phone": ""
    },
    {
      "name": "Dr. Amrish K. Panwar",
      "email": "panwaramar@gmail.com",
      "phone": ""
    },
    {
      "name": "Dr. Bharti Singh",
      "email": "bhartisingh@dtu.ac.in",
      "phone": ""
    },
    {
      "name": "Dr. Sarita Baghel",
      "email": "saritabaghel@dtu.ac.in",
      "phone": ""
    },
    {
      "name": "Dr. Richa Sharma",
      "email": "richasharma@dtu.ac.in",
      "phone": ""
    },
    {
      "name": "Dr. Mukhtiyar Singh",
      "email": "mukhtiyarsingh@dtu.ac.in",
      "phone": ""
    },
    {
      "name": "Yogendra Kumar Meena",
      "email": "yogendra.meena@dtu.ac.in",
      "phone": ""
    },
    {
      "name": "Dr. R. K. Sinha",
      "email": "rksinha@dtu.ac.in",
      "phone": ""
    },
    {
      "name": "Dr. R. K. Sinha",
      "email": "dr_rk_sinha@yahoo.com",
      "phone": ""
    },
    {
      "name": "Dr. H K Singh",
      "email": "hksingh@dtu.ac.in",
      "phone": ""
    },
    {
      "name": "Honorary Faculty",
      "email": "hbbohidar@jnu.ac.in",
      "phone": ""
    },
    {
      "name": "Dr. Kamal Kishor",
      "email": "kamalkishor@dce.ac.in",
      "phone": ""
    },
    {
      "name": "Dr.  Bharat Bajaj",
      "email": "bharatbajaj@dtu.ac.in",
      "phone": ""
    },
    {
      "name": "Dr. Mukesh Kumari",
      "email": "mukshi87@gmail.com",
      "phone": ""
    },
    {
      "name": "Dr. Vinay Kumar",
      "email": "vnykmr7@gmail.com",
      "phone": ""
    },
    {
      "name": "Dr. Neha Gupta",
      "email": "nehagpt2105@gmail.com",
      "phone": ""
    },
    {
      "name": "Dr. Lucky Krishnia",
      "email": "lucky.krishnia@gmail.com",
      "phone": ""
    },
    {
      "name": "Dr. Sameer Jain",
      "email": "ferro_2005_sam@yahoo.co.in",
      "phone": ""
    },
    {
      "name": "Dr. Ravi Gupta",
      "email": "ravigpt0709@gmail.com",
      "phone": ""
    },
    {
      "name": "Dr. Ratneshwar Kumar Ratnesh",
      "email": "ratnes123@gmail.com",
      "phone": ""
    },
    {
      "name": "Head of Department",
      "email": "yashahasija@dtu.ac.in",
      "phone": ""
    },
    {
      "name": "Prof. Pravir Kumar",
      "email": "pravirkumar@dtu.ac.in",
      "phone": ""
    },
    {
      "name": "Prof. Jai Gopal Sharma",
      "email": "sharmajaigopal@gmail.com",
      "phone": ""
    },
    {
      "name": "Prof. Jai Gopal Sharma",
      "email": "sharmajaigopal@dce.ac.in",
      "phone": ""
    },
    {
      "name": "Prof. Bansi Dhar Malhotra",
      "email": "bansi.malhotra@gmail.com",
      "phone": ""
    },
    {
      "name": "Prof. Bansi Dhar Malhotra",
      "email": "bansi.malhotra@dce.ac.in",
      "phone": ""
    },
    {
      "name": "Associate Professor",
      "email": "navneetab@dce.ac.in",
      "phone": ""
    },
    {
      "name": "Dr. Nirala Ramchiary",
      "email": "nrudsc@gmail.com",
      "phone": ""
    },
    {
      "name": "Dr. Raman Kumar",
      "email": "ramankumar@dtu.ac.in",
      "phone": ""
    },
    {
      "name": "Dr. Prem Raj Meena",
      "email": "prmeena@dtu.ac.in",
      "phone": ""
    },
    {
      "name": "Dr. Mamta Rani",
      "email": "mamtarani@dtu.ac.in",
      "phone": ""
    },
    {
      "name": "Dr. Praveen Kumar",
      "email": "kumarpraveen@dtu.ac.in",
      "phone": ""
    },
    {
      "name": "Dr. Shivani Khatri",
      "email": "shivanikhatri@dtu.ac.in",
      "phone": ""
    },
    {
      "name": "Dr. Ankita",
      "email": "ankitatehlan@dtu.ac.in",
      "phone": ""
    },
    {
      "name": "Dr. Rashmi Kataria",
      "email": "rashmikataria@gmail.com",
      "phone": ""
    },
    {
      "name": "Dr. Simran Bhullar",
      "email": "simranbhullar@dtu.ac.in",
      "phone": ""
    },
    {
      "name": "Dr. Smita Rastogi Verma",
      "email": "smitar@dtu.ac.in",
      "phone": ""
    },
    {
      "name": "Dr. Saurabh C Saxena",
      "email": "saurabhcsaxena@dtu.ac.in",
      "phone": ""
    },
    {
      "name": "Dr. Prakash Chandra",
      "email": "prakashchandra@dtu.ac.in",
      "phone": ""
    },
    {
      "name": "Dr. Kriti Bhandari",
      "email": "kritibhandari@dtu.ac.in",
      "phone": ""
    },
    {
      "name": "anil",
      "email": "anil@dtu.ac.in",
      "phone": ""
    },
    {
      "name": "parihar.anil",
      "email": "parihar.anil@gmail.com",
      "phone": ""
    },
    {
      "name": "rkyadav",
      "email": "rkyadav@dtu.ac.in",
      "phone": ""
    },
    {
      "name": "rajnijindal",
      "email": "rajnijindal@dce.ac.in",
      "phone": ""
    },
    {
      "name": "vinod_k",
      "email": "vinod_k@dtu.ac.in",
      "phone": ""
    },
    {
      "name": "mkg1109",
      "email": "mkg1109@rediffmail.com",
      "phone": ""
    },
    {
      "name": "mkumarg",
      "email": "mkumarg@dce.ac.in",
      "phone": ""
    },
    {
      "name": "rahulkatarya",
      "email": "rahulkatarya@dtu.ac.in",
      "phone": ""
    },
    {
      "name": "rahuldtu",
      "email": "rahuldtu@gmail.com",
      "phone": ""
    },
    {
      "name": "shailenderkumar.verma",
      "email": "shailenderkumar.verma@gmail.com",
      "phone": ""
    },
    {
      "name": "nipunbansal",
      "email": "nipunbansal@dtu.ac.in",
      "phone": ""
    },
    {
      "name": "minnijain",
      "email": "minnijain@dtu.ac.in",
      "phone": ""
    },
    {
      "name": "sanjay.kumar",
      "email": "sanjay.kumar@dtu.ac.in",
      "phone": ""
    },
    {
      "name": "rohitbeniwal",
      "email": "rohitbeniwal@dtu.ac.in",
      "phone": ""
    },
    {
      "name": "prashant.shambharkar",
      "email": "prashant.shambharkar@dtu.ac.in",
      "phone": ""
    },
    {
      "name": "rajeevkumar",
      "email": "rajeevkumar@dtu.ac.in",
      "phone": ""
    },
    {
      "name": "pawansingh",
      "email": "pawansingh@dtu.ac.in",
      "phone": ""
    },
    {
      "name": "snigdhaagrawal",
      "email": "snigdhaagrawal@dtu.ac.in",
      "phone": ""
    },
    {
      "name": "moirangthembikensingh",
      "email": "moirangthembikensingh@dtu.ac.in",
      "phone": ""
    },
    {
      "name": "dgupta",
      "email": "dgupta@dce.ac.in",
      "phone": ""
    },
    {
      "name": "rsreejeth",
      "email": "rsreejeth@dtu.ac.in",
      "phone": ""
    },
    {
      "name": "saxena58",
      "email": "saxena58@gmail.com",
      "phone": ""
    },
    {
      "name": "manojsethi",
      "email": "manojsethi@dce.ac.in",
      "phone": ""
    },
    {
      "name": "Head of Department",
      "email": "awadheshg@gmail.com",
      "phone": ""
    },
    {
      "name": "atrivedi",
      "email": "atrivedi@dce.ac.in",
      "phone": ""
    },
    {
      "name": "akgupta",
      "email": "akgupta@dce.edu",
      "phone": ""
    },
    {
      "name": "nirendradev",
      "email": "nirendradev@dce.ac.in",
      "phone": ""
    },
    {
      "name": "akgupta",
      "email": "akgupta@dce.ac.in",
      "phone": ""
    },
    {
      "name": "sahuanilkr",
      "email": "sahuanilkr@yahoo.co.in",
      "phone": ""
    },
    {
      "name": "rakeshkumar",
      "email": "rakeshkumar@dce.ac.in",
      "phone": ""
    },
    {
      "name": "Dr. Amit Kr. Shrivastava",
      "email": "aksrivastava@dce.ac.in",
      "phone": ""
    },
    {
      "name": "Alok Verma",
      "email": "alokverma@dce.ac.in",
      "phone": ""
    },
    {
      "name": "Naresh Kumar",
      "email": "nareshkumar@dce.ac.in",
      "phone": ""
    },
    {
      "name": "Dr.  S. Anbu Kumar",
      "email": "sanbukumar@dce.ac.in",
      "phone": ""
    },
    {
      "name": "rakesh1653",
      "email": "rakesh1653@gmail.com",
      "phone": ""
    },
    {
      "name": "gpawadhiya",
      "email": "gpawadhiya@dce.ac.in",
      "phone": ""
    },
    {
      "name": "Susheel Kumar",
      "email": "susheelkumar@dce.ac.in",
      "phone": ""
    },
    {
      "name": "Narad Muni Prasad",
      "email": "nmprasad@dce.ac.in",
      "phone": ""
    },
    {
      "name": "A. R. Kongan",
      "email": "arkongan@dce.ac.in",
      "phone": ""
    },
    {
      "name": "B.R.G. Robert",
      "email": "brgrobert@dce.ac.in",
      "phone": ""
    },
    {
      "name": "B. Jhamnani",
      "email": "bjhamnani@dce.ac.in",
      "phone": ""
    },
    {
      "name": "Dr Bharat Jhamnani",
      "email": "bjhamnani@gmail.com",
      "phone": ""
    },
    {
      "name": "Dr. Ritu Raj",
      "email": "rituraj.ahirwar@gmail.com",
      "phone": ""
    },
    {
      "name": "Hrishikesh Dubey",
      "email": "dubeyrishi018@gmail.com",
      "phone": ""
    },
    {
      "name": "saurabh.agrawal",
      "email": "saurabh.agrawal@dtu.ac.in",
      "phone": ""
    },
    {
      "name": "Professor",
      "email": "pksuri@dtu.ac.in",
      "phone": ""
    },
    {
      "name": "rajanyadav",
      "email": "rajanyadav@dtu.ac.in",
      "phone": ""
    },
    {
      "name": "gcmaheshwari2004",
      "email": "gcmaheshwari2004@yahoo.com",
      "phone": ""
    },
    {
      "name": "neeraj.sharma",
      "email": "neeraj.sharma@dtu.ac.in",
      "phone": ""
    },
    {
      "name": "Associate Professor",
      "email": "archanasingh@dtu.ac.in",
      "phone": ""
    },
    {
      "name": "Shikhan.khera",
      "email": "Shikhan.khera@dtu.ac.in",
      "phone": ""
    },
    {
      "name": "abhinavchaudhary",
      "email": "abhinavchaudhary@dtu.ac.in",
      "phone": ""
    },
    {
      "name": "chandansharma",
      "email": "chandansharma@dtu.ac.in",
      "phone": ""
    },
    {
      "name": "kusumlata",
      "email": "kusumlata@dtu.ac.in",
      "phone": ""
    },
    {
      "name": "gaganmeetkaur.awal",
      "email": "gaganmeetkaur.awal@dtu.ac.in",
      "phone": ""
    },
    {
      "name": "pramavishnoi",
      "email": "pramavishnoi@dtu.ac.in",
      "phone": ""
    },
    {
      "name": "veenushankar",
      "email": "veenushankar@dtu.ac.in",
      "phone": ""
    },
    {
      "name": "arushijain",
      "email": "arushijain@dtu.ac.in",
      "phone": ""
    },
    {
      "name": "narendrakumar",
      "email": "narendrakumar@dtu.ac.in",
      "phone": ""
    },
    {
      "name": "Dr. Madhusudan Singh",
      "email": "madhusudan@dce.ac.in",
      "phone": ""
    },
    {
      "name": "Dr.Uma Nangia",
      "email": "umanangia@dce.ac.in",
      "phone": ""
    },
    {
      "name": "Dr. Rachna Garg",
      "email": "rachnagarg@dce.ac.in",
      "phone": ""
    },
    {
      "name": "narendra.kumar",
      "email": "narendra.kumar@dtu.ac.in",
      "phone": ""
    },
    {
      "name": "Dr.Vishal Verma",
      "email": "vishalverma@dce.ac.in",
      "phone": ""
    },
    {
      "name": "Dr. Suman Bhowmick",
      "email": "suman.bhowmick@dce.ac.in",
      "phone": ""
    },
    {
      "name": "Dr. Bharat Bhushan",
      "email": "bharat@dce.ac.in",
      "phone": ""
    },
    {
      "name": "Dr. S. T. Nagarajan",
      "email": "stnagarajan@dce.ac.in",
      "phone": ""
    },
    {
      "name": "Dr. Mukhtiar Singh",
      "email": "mukhtiarsingh@dce.ac.in",
      "phone": ""
    },
    {
      "name": "Dr. Dheeraj Joshi",
      "email": "joshidheeraj@dce.ac.in",
      "phone": ""
    },
    {
      "name": "Dr.  J. N. Rai",
      "email": "jnrai@dce.ac.in",
      "phone": ""
    },
    {
      "name": "Dr.    Sudarshan Kumar Babu Valluru",
      "email": "sudarshan_valluru@dce.ac.in",
      "phone": ""
    },
    {
      "name": "Dr. Ram Bhagat",
      "email": "rambhagat@dce.ac.in",
      "phone": ""
    },
    {
      "name": "Dr.Vinod Kumar Yadav",
      "email": "vinodkumar@dtu.ac.in",
      "phone": ""
    },
    {
      "name": "Dr .N. K. Jain",
      "email": "nkjain@dtu.ac.in",
      "phone": ""
    },
    {
      "name": "Dr.  R. Saha",
      "email": "rshahacno@yahoo.com",
      "phone": ""
    },
    {
      "name": "Dr. D. R. Bhaskar",
      "email": "drbhaskhar@dtu.ac.in",
      "phone": ""
    },
    {
      "name": "Dr. Duli Chand Meena",
      "email": "dcmeena@dce.ac.in",
      "phone": ""
    },
    {
      "name": "Ramjee Lal Meena",
      "email": "meenarl@dtu.ac.in",
      "phone": ""
    },
    {
      "name": "Dr. Prem Prakash",
      "email": "premprakash@dtu.ac.in",
      "phone": ""
    },
    {
      "name": "Dr.  Garima",
      "email": "garimasolanki@dtu.ac.in",
      "phone": ""
    },
    {
      "name": "Dr. Bhavnesh Jaint",
      "email": "bhavneshjaint@dtu.ac.in",
      "phone": ""
    },
    {
      "name": "Assistant Professor",
      "email": "a.b.bhattacharya@dtu.ac.in",
      "phone": ""
    },
    {
      "name": "Dr.  Ashish Rajeshwar Kulkarni",
      "email": "ashishkulkarni@dtu.ac.in",
      "phone": ""
    },
    {
      "name": "Dr. Anup Kumar Mandpura",
      "email": "kanup@dtu.ac.in",
      "phone": ""
    },
    {
      "name": "Dr. Ankita Arora",
      "email": "aroraankita@dtu.ac.in",
      "phone": ""
    },
    {
      "name": "Himanshu Singh",
      "email": "himanshusingh@dtu.ac.in",
      "phone": ""
    },
    {
      "name": "Saurabh Mishra",
      "email": "saurabhmishra@dtu.ac.in",
      "phone": ""
    },
    {
      "name": "Dr. Rajesh Kumar",
      "email": "rajeshkumar@dtu.ac.in",
      "phone": ""
    },
    {
      "name": "Dr. Mayank Kumar",
      "email": "mayankkumar@dtu.ac.in",
      "phone": ""
    },
    {
      "name": "Dr. Prakash Chittora",
      "email": "prakashchittora@dtu.ac.in",
      "phone": ""
    },
    {
      "name": "Dr.  Shatakshi",
      "email": "shatakshi18jha@gmail.com",
      "phone": ""
    },
    {
      "name": "Abhishek Chaudhary",
      "email": "abhishek@dtu.ac.in",
      "phone": ""
    },
    {
      "name": "Anupama",
      "email": "anupama@dtu.ac.in",
      "phone": ""
    },
    {
      "name": "Krishna Dutt",
      "email": "krishna@dtu.ac.in",
      "phone": ""
    },
    {
      "name": "Rohan Pillai",
      "email": "rohan92@dtu.ac.in",
      "phone": ""
    },
    {
      "name": "Dr. Vanjari Venkata Ramana",
      "email": "venkata@dtu.ac.in",
      "phone": ""
    },
    {
      "name": "mmtripathi",
      "email": "mmtripathi@dce.ac.in",
      "phone": ""
    },
    {
      "name": "priyamahajan",
      "email": "priyamahajan@dtu.ac.in",
      "phone": ""
    },
    {
      "name": "nkbhagat",
      "email": "nkbhagat@dce.ac.in",
      "phone": ""
    },
    {
      "name": "Dr Rinchin W. Mosobi",
      "email": "wangzom@dtu.ac.in",
      "phone": ""
    },
    {
      "name": "Dr. Madan Mohan Rayguru",
      "email": "mmrayguru@dtu.ac.in",
      "phone": ""
    },
    {
      "name": "Ms. Monika Verma",
      "email": "verma15.monika@gmail.com",
      "phone": ""
    },
    {
      "name": "neetapandey",
      "email": "neetapandey@dce.ac.in",
      "phone": ""
    },
    {
      "name": "Professor",
      "email": "asokde@dce.edu",
      "phone": ""
    },
    {
      "name": "rajivkapoor",
      "email": "rajivkapoor@dce.ac.in",
      "phone": ""
    },
    {
      "name": "opverma",
      "email": "opverma@dce.ac.in",
      "phone": ""
    },
    {
      "name": "s.indu",
      "email": "s.indu@dce.ac.in",
      "phone": ""
    },
    {
      "name": "nsraghava",
      "email": "nsraghava@dtu.ac.in",
      "phone": ""
    },
    {
      "name": "rpandey",
      "email": "rpandey@dce.ac.in",
      "phone": ""
    },
    {
      "name": "Prof. Jeebananda Panda",
      "email": "jpanda@dce.ac.in",
      "phone": ""
    },
    {
      "name": "Prof. Rajesh Rohilla",
      "email": "rajesh@dce.ac.in",
      "phone": ""
    },
    {
      "name": "Prof. Dinesh Kumar",
      "email": "dineshkumar@dtu.ac.in",
      "phone": ""
    },
    {
      "name": "Prof. Dinesh Kumar",
      "email": "dinesh_chutani@yahoo.com",
      "phone": ""
    },
    {
      "name": "Prof. M S Choudhary",
      "email": "msc_1976@yahoo.com",
      "phone": ""
    },
    {
      "name": "Prof.  Alok Kumar Singh",
      "email": "aksingh@dce.ac.in",
      "phone": ""
    },
    {
      "name": "Prof. Priyanka Jain",
      "email": "priyajain2000@rediffmail.com",
      "phone": ""
    },
    {
      "name": "Dr. Gurjit Kaur",
      "email": "gurjitkaur@dtu.ac.in",
      "phone": ""
    },
    {
      "name": "Associate Professor",
      "email": "rbirok@gmail.com",
      "phone": ""
    },
    {
      "name": "Dr. Deva Nand",
      "email": "devkamboj@dce.ac.in",
      "phone": ""
    },
    {
      "name": "Dr. Sudipta Majumdar",
      "email": "korsudipta@rediffmail.com",
      "phone": ""
    },
    {
      "name": "Dr Avinash Ratre",
      "email": "avinashratre@dtu.ac.in",
      "phone": ""
    },
    {
      "name": "Dr. Ajai Kumar Gautam",
      "email": "ajai.gautam@gmail.com",
      "phone": ""
    },
    {
      "name": "Piyush Tewari",
      "email": "piyushtewari@dtu.ac.in",
      "phone": ""
    },
    {
      "name": "Anurag Chauhan",
      "email": "anuragchauhan@dtu.ac.in",
      "phone": ""
    },
    {
      "name": "Anand Kumar",
      "email": "anandkumar@dtu.ac.in",
      "phone": ""
    },
    {
      "name": "Dr. Kriti Suneja",
      "email": "kritisuneja@dtu.ac.in",
      "phone": ""
    },
    {
      "name": "Sumit Kumar Khandelwal",
      "email": "sumit.khandelwal@dtu.ac.in",
      "phone": ""
    },
    {
      "name": "Dr Rohit Kumar",
      "email": "rohit.kumar@dtu.ac.in",
      "phone": ""
    },
    {
      "name": "Sachin Dhariwal",
      "email": "sachindhariwal@dtu.ac.in",
      "phone": ""
    },
    {
      "name": "Akshay Mann",
      "email": "akshay.mann@dtu.ac.in",
      "phone": ""
    },
    {
      "name": "Lokesh Gautam",
      "email": "lokeshgautam21@gmail.com",
      "phone": ""
    },
    {
      "name": "Dr. Rahul Thakur",
      "email": "rahulthakur@dtu.ac.in",
      "phone": ""
    },
    {
      "name": "Kaustubh Ranjan Singh",
      "email": "kaustubh@dtu.ac.in",
      "phone": ""
    },
    {
      "name": "Dr. Sachin Taran",
      "email": "taransachin2@gmail.com",
      "phone": ""
    },
    {
      "name": "Dr. Sumit Kale",
      "email": "sumitkale785@gmail.com",
      "phone": ""
    },
    {
      "name": "Dr. Sonal Singh",
      "email": "sonal.singh0811@gmail.com",
      "phone": ""
    },
    {
      "name": "Dr Anukul Pandey",
      "email": "anukul66@gmail.com",
      "phone": ""
    },
    {
      "name": "Lavi Tanwar",
      "email": "lavi.tanwar02@gmail.com",
      "phone": ""
    },
    {
      "name": "Dr. Chhavi Dhiman",
      "email": "chhavi.dhiman@dtu.ac.in",
      "phone": ""
    },
    {
      "name": "Dr. Sonam Rewari",
      "email": "rewarisonam@gmail.com",
      "phone": ""
    },
    {
      "name": "Mr. Varun Sangwan",
      "email": "varunsangwan@dtu.ac.in",
      "phone": ""
    },
    {
      "name": "Mr. Vinay Kumar",
      "email": "ankvin@gmail.com",
      "phone": ""
    },
    {
      "name": "Dr. Pankaj Dahiya",
      "email": "pankajdahiya@dtu.ac.in",
      "phone": ""
    },
    {
      "name": "akgupta",
      "email": "akgupta@dtu.ac.in",
      "phone": ""
    },
    {
      "name": "akharitash",
      "email": "akharitash@dce.ac.in",
      "phone": ""
    },
    {
      "name": "rajeevmishraiitr",
      "email": "rajeevmishraiitr@gmail.com",
      "phone": ""
    },
    {
      "name": "harshpipil",
      "email": "harshpipil@dtu.ac.in",
      "phone": ""
    },
    {
      "name": "ravijadon",
      "email": "ravijadon@dtu.ac.in",
      "phone": ""
    },
    {
      "name": "barunkanoo",
      "email": "barunkanoo@dtu.ac.in",
      "phone": ""
    },
    {
      "name": "sandeepkumar",
      "email": "sandeepkumar@dtu.ac.in",
      "phone": ""
    },
    {
      "name": "prateeksaini",
      "email": "prateeksaini@dtu.ac.in",
      "phone": ""
    },
    {
      "name": "hariom.jorwal",
      "email": "hariom.jorwal@dtu.ac.in",
      "phone": ""
    },
    {
      "name": "rajatchatterjee",
      "email": "rajatchatterjee@dtu.ac.in",
      "phone": ""
    },
    {
      "name": "Head of Department",
      "email": "sarojbala@dtu.ac.in",
      "phone": ""
    },
    {
      "name": "Professor",
      "email": "seemasingh@dce.ac.in",
      "phone": ""
    },
    {
      "name": "seemasinghdce",
      "email": "seemasinghdce@yahoo.com",
      "phone": ""
    },
    {
      "name": "seemasinghdtu",
      "email": "seemasinghdtu@gmail.com",
      "phone": ""
    },
    {
      "name": "nandkumar",
      "email": "nandkumar@dce.ac.in",
      "phone": ""
    },
    {
      "name": "nand.dce",
      "email": "nand.dce@gmail.com",
      "phone": ""
    },
    {
      "name": "rajivdwivedi",
      "email": "rajivdwivedi@dtu.ac.in",
      "phone": ""
    },
    {
      "name": "Assistant Professor",
      "email": "parinitasinha@dtu.ac.in",
      "phone": ""
    },
    {
      "name": "dinesh",
      "email": "dinesh@dtu.ac.in",
      "phone": ""
    },
    {
      "name": "dvishwakarma",
      "email": "dvishwakarma@gmail.com",
      "phone": ""
    },
    {
      "name": "kapil",
      "email": "kapil@ieee.org",
      "phone": ""
    },
    {
      "name": "seba_406",
      "email": "seba_406@yahoo.in",
      "phone": ""
    },
    {
      "name": "drvirender.ranga",
      "email": "drvirender.ranga@gmail.com",
      "phone": ""
    },
    {
      "name": "rituagarwal",
      "email": "rituagarwal@dtu.ac.in",
      "phone": ""
    },
    {
      "name": "letter4ana",
      "email": "letter4ana@gmail.com",
      "phone": ""
    },
    {
      "name": "priyankameel",
      "email": "priyankameel@dtu.ac.in",
      "phone": ""
    },
    {
      "name": "jasrajmeena",
      "email": "jasrajmeena@dtu.ac.in",
      "phone": ""
    },
    {
      "name": "rahul_gupta",
      "email": "rahul_gupta@dtu.ac.in",
      "phone": ""
    },
    {
      "name": "binduverma",
      "email": "binduverma@dtu.ac.in",
      "phone": ""
    },
    {
      "name": "varsha",
      "email": "varsha@dtu.ac.in",
      "phone": ""
    },
    {
      "name": "ankityadav",
      "email": "ankityadav@dtu.ac.in",
      "phone": ""
    },
    {
      "name": "ashutoshpandey",
      "email": "ashutoshpandey@dtu.ac.in",
      "phone": ""
    },
    {
      "name": "shally.gupta",
      "email": "shally.gupta@dtu.ac.in",
      "phone": ""
    },
    {
      "name": "akshay.mool",
      "email": "akshay.mool@dtu.ac.in",
      "phone": ""
    },
    {
      "name": "anita.thakur",
      "email": "anita.thakur@dtu.ac.in",
      "phone": ""
    },
    {
      "name": "geetanjali.getz",
      "email": "geetanjali.getz@gmail.com",
      "phone": ""
    },
    {
      "name": "Head of Department",
      "email": "bbarora@dce.ac.in",
      "phone": ""
    },
    {
      "name": "Professor",
      "email": "skgarg@dce.ac.in",
      "phone": ""
    },
    {
      "name": "Prof. Vipin",
      "email": "vipin@dce.ac.in",
      "phone": ""
    },
    {
      "name": "Prof. D.S. Nagesh",
      "email": "dsnagesh@dce.edu",
      "phone": ""
    },
    {
      "name": "samsher",
      "email": "samsher@dce.ac.in",
      "phone": ""
    },
    {
      "name": "Prof. Reeta Wattal",
      "email": "reetawattal@dce.ac.in",
      "phone": ""
    },
    {
      "name": "Prof.   Raj Kumar Singh",
      "email": "rajkumarsingh@dce.ac.in",
      "phone": ""
    },
    {
      "name": "Prof. Amit Pal",
      "email": "amitpal@dce.ac.in",
      "phone": ""
    },
    {
      "name": "Prof. R.C. Singh",
      "email": "rcsingh@dce.ac.in",
      "phone": ""
    },
    {
      "name": "Prof. Ranganath M. Singari",
      "email": "ranganath@dce.ac.in",
      "phone": ""
    },
    {
      "name": "Prof. Rajesh Kumar",
      "email": "dr.rajeshmits@gmail.com",
      "phone": ""
    },
    {
      "name": "waliaravinder",
      "email": "waliaravinder@yahoo.com",
      "phone": ""
    },
    {
      "name": "Prof. Qasim Murtaza",
      "email": "qasimmurtaza@dce.ac.in",
      "phone": ""
    },
    {
      "name": "Prof. Rajiv Chaudhary",
      "email": "rajivchaudhary@dce.ac.in",
      "phone": ""
    },
    {
      "name": "Prof. Atul Kumar Agarwal",
      "email": "atulkumaragarwal@dce.ac.in",
      "phone": ""
    },
    {
      "name": "Prof.  Vijay Gautam",
      "email": "vijaygautam@dce.ac.in",
      "phone": ""
    },
    {
      "name": "Prof. Akhilesh Arora",
      "email": "akhilesharora@dce.ac.in",
      "phone": ""
    },
    {
      "name": "Prof. Anil Kumar",
      "email": "anilkumar76@dtu.ac.in",
      "phone": ""
    },
    {
      "name": "Prof. R.S. Mishra",
      "email": "rsmishra@dce.ac.in",
      "phone": ""
    },
    {
      "name": "Emeritus Professor",
      "email": "smaji@dce.ac.in",
      "phone": ""
    },
    {
      "name": "Dr.  Ashok Kumar Madan",
      "email": "ashokmadan@dce.ac.in",
      "phone": ""
    },
    {
      "name": "Associate Professor",
      "email": "vishwakamal@dce.ac.in",
      "phone": ""
    },
    {
      "name": "P.K. Jain",
      "email": "pkjain@dce.ac.in",
      "phone": ""
    },
    {
      "name": "P.V. Ram Kumar",
      "email": "pvramkumar@dce.ac.in",
      "phone": ""
    },
    {
      "name": "Dr.  Krovvidi Srinivas",
      "email": "srinivaskrovvidi@dtu.ac.in",
      "phone": ""
    },
    {
      "name": "V. Jeganathan Arulmoni",
      "email": "v.jeganathan.dce@gmail.com",
      "phone": ""
    },
    {
      "name": "Dr. Manjunath K",
      "email": "manjukmys@gmail.com",
      "phone": ""
    },
    {
      "name": "Dr. Mohammad Zunaid",
      "email": "mzunaid@dtu.ac.in",
      "phone": ""
    },
    {
      "name": "Dr. Raghavendra Gautam",
      "email": "raghvendrag80@yahoo.com",
      "phone": ""
    },
    {
      "name": "Dr. Paras Kumar",
      "email": "paraskumar@dtu.ac.in",
      "phone": ""
    },
    {
      "name": "Sushila Rani",
      "email": "sranidtu@gmail.com",
      "phone": ""
    },
    {
      "name": "Assistant Professor",
      "email": "yuvraj@dce.ac.in",
      "phone": ""
    },
    {
      "name": "Dr. Bijendra Prasad",
      "email": "bijendraprasad@dtu.ac.in",
      "phone": ""
    },
    {
      "name": "amit",
      "email": "amit@dtu.ac.in",
      "phone": ""
    },
    {
      "name": "Dr. Sandeep Kumar",
      "email": "sandeep.kumar@dtu.ac.in",
      "phone": ""
    },
    {
      "name": "Dr. Satyajit Sahu",
      "email": "satyajitsahu@dtu.ac.in",
      "phone": ""
    },
    {
      "name": "Dr. Puneet Singh Gautam",
      "email": "puneetsingh@dtu.ac.in",
      "phone": ""
    },
    {
      "name": "Dr. Nitin Dixit",
      "email": "nitindixit@dtu.ac.in",
      "phone": ""
    },
    {
      "name": "Dr. Ankur Sharma",
      "email": "ankursharma@dtu.ac.in",
      "phone": ""
    },
    {
      "name": "Dr. Anil Singh",
      "email": "anilsingh@dtu.ac.in",
      "phone": ""
    },
    {
      "name": "Dr. Rajendra Prasad Meena",
      "email": "rajendraprasad@dtu.ac.in",
      "phone": ""
    },
    {
      "name": "Dr. Sumit Singh",
      "email": "sumit.singh@dtu.ac.in",
      "phone": ""
    },
    {
      "name": "Dr. Kashish Kumar",
      "email": "kashishkumar@dtu.ac.in",
      "phone": ""
    },
    {
      "name": "Dr. Kapil Chaudhri",
      "email": "kapilchaudhri@dtu.ac.in",
      "phone": ""
    },
    {
      "name": "Dr. Abhishek Kumar",
      "email": "abhishek.kumar@dtu.ac.in",
      "phone": ""
    },
    {
      "name": "Dr. Jyotsna Gupta",
      "email": "jyotsnagupta@dtu.ac.in",
      "phone": ""
    },
    {
      "name": "Dr. Tarun Pratap Singh",
      "email": "tarun.pratap@dtu.ac.in",
      "phone": ""
    },
    {
      "name": "Dr. Dipayan Das",
      "email": "dipayandas@dtu.ac.in",
      "phone": ""
    },
    {
      "name": "Dr. Anant Bhardwaj",
      "email": "anantbhardwaj@dtu.ac.in",
      "phone": ""
    },
    {
      "name": "Dr. Sumit Joshi",
      "email": "sumitjoshi@dtu.ac.in",
      "phone": ""
    },
    {
      "name": "Dr. Manish Kumar",
      "email": "manishkumar@dtu.ac.in",
      "phone": ""
    },
    {
      "name": "Dr. Sharaf U Nisa",
      "email": "sharafunisa@dtu.ac.in",
      "phone": ""
    },
    {
      "name": "Dr. ASHISH KUMAR MISHRA",
      "email": "ASHISH@DTU.AC.IN",
      "phone": ""
    },
    {
      "name": "Kapil Kumar",
      "email": "kapil.kumar@dtu.ac.in",
      "phone": ""
    },
    {
      "name": "Dr. Saurabh Agrawal",
      "email": "agrawals.iit@gmail.com",
      "phone": ""
    },
    {
      "name": "Ravi Butola",
      "email": "ravimed@dtu.ac.in",
      "phone": ""
    },
    {
      "name": "Contractual  Faculty",
      "email": "skdas4321@rediffmail.com",
      "phone": ""
    },
    {
      "name": "ruchikamalhotra",
      "email": "ruchikamalhotra@dtu.ac.in",
      "phone": ""
    },
    {
      "name": "divyashikha",
      "email": "divyashikha@dtu.ac.in",
      "phone": ""
    },
    {
      "name": "sanjaypatidar",
      "email": "sanjaypatidar@dtu.ac.in",
      "phone": ""
    },
    {
      "name": "shwetameena",
      "email": "shwetameena@dtu.ac.in",
      "phone": ""
    },
    {
      "name": "rammurtiieju05",
      "email": "rammurtiieju05@gmail.com",
      "phone": ""
    },
    {
      "name": "geetanjali.garg",
      "email": "geetanjali.garg@dtu.ac.in",
      "phone": ""
    },
    {
      "name": "geeta.anjali.garg",
      "email": "geeta.anjali.garg@gmail.com",
      "phone": ""
    },
    {
      "name": "Assistant Professor",
      "email": "neerajrathi@dtu.ac.in",
      "phone": ""
    },
    {
      "name": "parthapratimdas",
      "email": "parthapratimdas@dtu.ac.in",
      "phone": ""
    },
    {
      "name": "varunsingh",
      "email": "varunsingh@dtu.ac.in",
      "phone": ""
    },
    {
      "name": "ravi.ud2017",
      "email": "ravi.ud2017@gmail.com",
      "phone": ""
    },
    {
      "name": "gulistaan",
      "email": "gulistaan@dtu.ac.in",
      "phone": ""
    },
    {
      "name": "debarghyakumar",
      "email": "debarghyakumar@dtu.ac.in",
      "phone": ""
    },
    {
      "name": "deepika.kashyap",
      "email": "deepika.kashyap@dtu.ac.in",
      "phone": ""
    },
    {
      "name": "lkdas",
      "email": "lkdas@dtu.ac.in",
      "phone": ""
    },
    {
      "name": "sgranjan09",
      "email": "sgranjan09@gmail.com",
      "phone": ""
    },
    {
      "name": "amookerjee",
      "email": "amookerjee@dtu.ac.in",
      "phone": ""
    },
    {
      "name": "bhanumurthykv",
      "email": "bhanumurthykv@yahoo.com",
      "phone": ""
    },
    {
      "name": "prof.mksharma",
      "email": "prof.mksharma@dtu.ac.in",
      "phone": ""
    },
    {
      "name": "askmittal",
      "email": "askmittal@yahoo.com",
      "phone": ""
    },
    {
      "name": "ssingh.pk",
      "email": "ssingh.pk@gmail.com",
      "phone": ""
    },
    {
      "name": "rajiv.arora",
      "email": "rajiv.arora@nic.in",
      "phone": ""
    },
    {
      "name": "nidhimaheshwari",
      "email": "nidhimaheshwari@dtu.ac.in",
      "phone": ""
    },
    {
      "name": "shikhankhera",
      "email": "shikhankhera@yahoo.co.in",
      "phone": ""
    },
    {
      "name": "jagvinder.singh",
      "email": "jagvinder.singh@dtu.ac.in",
      "phone": ""
    },
    {
      "name": "anurag.chaturvedi",
      "email": "anurag.chaturvedi@dtu.ac.in",
      "phone": ""
    },
    {
      "name": "priyamalhotra",
      "email": "priyamalhotra@dtu.ac.in",
      "phone": ""
    },
    {
      "name": "harleenkaur",
      "email": "harleenkaur@dtu.ac.in",
      "phone": ""
    },
    {
      "name": "versha.sehgal",
      "email": "versha.sehgal@dtu.ac.in",
      "phone": ""
    },
    {
      "name": "naval.garg",
      "email": "naval.garg@dtu.ac.in",
      "phone": ""
    },
    {
      "name": "deeptiaggrawal",
      "email": "deeptiaggrawal@dtu.ac.in",
      "phone": ""
    },
    {
      "name": "pallavi.kalra",
      "email": "pallavi.kalra@dtu.ac.in",
      "phone": ""
    },
    {
      "name": "darshankalasua",
      "email": "darshankalasua@dtu.ac.in",
      "phone": ""
    },
    {
      "name": "nehajain",
      "email": "nehajain@dtu.ac.in",
      "phone": ""
    },
    {
      "name": "divyamishra",
      "email": "divyamishra@dtu.ac.in",
      "phone": ""
    },
    {
      "name": "anushrutivagrani",
      "email": "anushrutivagrani@dtu.ac.in",
      "phone": ""
    },
    {
      "name": "sanjayyadav",
      "email": "sanjayyadav@dtu.ac.in",
      "phone": ""
    },
    {
      "name": "amandeepkaur",
      "email": "amandeepkaur@dtu.ac.in",
      "phone": ""
    },
    {
      "name": "ritikachopra",
      "email": "ritikachopra@dtu.ac.in",
      "phone": ""
    },
    {
      "name": "rahulbaghel",
      "email": "rahulbaghel@dtu.ac.in",
      "phone": ""
    },
    {
      "name": "sakshikukreja",
      "email": "sakshikukreja@dtu.ac.in",
      "phone": ""
    },
    {
      "name": "maansi.gupta",
      "email": "maansi.gupta@dtu.ac.in",
      "phone": ""
    },
    {
      "name": "sahil.bhukal",
      "email": "sahil.bhukal@dtu.ac.in",
      "phone": ""
    },
    {
      "name": "ratnam.mishra",
      "email": "ratnam.mishra@dtu.ac.in",
      "phone": ""
    },
    {
      "name": "aakanksha.kaushik",
      "email": "aakanksha.kaushik@dtu.ac.in",
      "phone": ""
    },
    {
      "name": "virender",
      "email": "virender@dtu.ac.in",
      "phone": ""
    },
    {
      "name": "puneet.arora",
      "email": "puneet.arora@dtu.ac.in",
      "phone": ""
    },
    {
      "name": "ankitagupta",
      "email": "ankitagupta@dtu.ac.in",
      "phone": ""
    },
    {
      "name": "shivaniyadav",
      "email": "shivaniyadav@dtu.ac.in",
      "phone": ""
    },
    {
      "name": "sucheta.sardar",
      "email": "sucheta.sardar@dtu.ac.in",
      "phone": ""
    },
    {
      "name": "rajesh.sharma",
      "email": "rajesh.sharma@dtu.ac.in",
      "phone": ""
    },
    {
      "name": "rakeshshankar",
      "email": "rakeshshankar@dtu.ac.in",
      "phone": ""
    },
    {
      "name": "sanjayb",
      "email": "sanjayb@dtu.ac.in",
      "phone": ""
    },
    {
      "name": "anshulujlayan",
      "email": "anshulujlayan@dtu.ac.in",
      "phone": ""
    }
  ],
  "all_emails": [
    "rksinha@dtu.ac.in",
    "aakanksha.kaushik@dtu.ac.in",
    "nrudsc@gmail.com",
    "shailenderkumar.verma@gmail.com",
    "dubeyrishi018@gmail.com",
    "drvirender.ranga@gmail.com",
    "ankitagupta@dtu.ac.in",
    "qasimmurtaza@dce.ac.in",
    "puneetsingh@dtu.ac.in",
    "tarun.pratap@dtu.ac.in",
    "prof.mksharma@dtu.ac.in",
    "jamkhongamtouthang@dtu.ac.in",
    "smitar@dtu.ac.in",
    "v.jeganathan.dce@gmail.com",
    "parinitasinha@dtu.ac.in",
    "rpandey@dce.ac.in",
    "anita.thakur@dtu.ac.in",
    "ratnam.mishra@dtu.ac.in",
    "ajai.gautam@gmail.com",
    "lavi.tanwar02@gmail.com",
    "askmittal@yahoo.com",
    "vinodkumar@dtu.ac.in",
    "tyagi_pawan@yahoo.co.in",
    "harshpipil@dtu.ac.in",
    "bharat@dce.ac.in",
    "sgranjan09@gmail.com",
    "rahuldtu@gmail.com",
    "sranidtu@gmail.com",
    "varunsingh@dtu.ac.in",
    "manishjain@dtu.ac.in",
    "priyamalhotra@dtu.ac.in",
    "trashagupta@gmail.com",
    "venkata@dtu.ac.in",
    "neetapandey@dce.ac.in",
    "susheelkumar@dce.ac.in",
    "chandansharma@dtu.ac.in",
    "asl213@gmail.com",
    "barunkanoo@dtu.ac.in",
    "taransachin2@gmail.com",
    "jpanda@dce.ac.in",
    "atrivedi@dce.ac.in",
    "devkamboj@dce.ac.in",
    "nehagpt2105@gmail.com",
    "Sangita_kansal15@rediffmail.com",
    "gaganmeetkaur.awal@dtu.ac.in",
    "apkaushik@gmail.com",
    "panwaramar@gmail.com",
    "asokde@dce.edu",
    "raghvendrag80@yahoo.com",
    "shivanikhatri@dtu.ac.in",
    "saxena58@gmail.com",
    "mmtripathi@dce.ac.in",
    "jyotsnagupta@dtu.ac.in",
    "bijendraprasad@dtu.ac.in",
    "debarghyakumar@dtu.ac.in",
    "arushijain@dtu.ac.in",
    "waliaravinder@yahoo.com",
    "sumitjoshi@dtu.ac.in",
    "anshularora@dtu.ac.in",
    "rashmikataria@gmail.com",
    "kritibhandari@dtu.ac.in",
    "letter4ana@gmail.com",
    "rajnijindal@dce.ac.in",
    "akharitash@dce.ac.in",
    "rsmishra@dce.ac.in",
    "mkumarg@dce.ac.in",
    "rajivdwivedi@dtu.ac.in",
    "ankvin@gmail.com",
    "nkbhagat@dce.ac.in",
    "Shikhan.khera@dtu.ac.in",
    "mukhtiyarsingh@dtu.ac.in",
    "varunsangwan@dtu.ac.in",
    "anukul66@gmail.com",
    "rchsharma@dce.ac.in",
    "mmrayguru@dtu.ac.in",
    "rajatchatterjee@dtu.ac.in",
    "geeta.anjali.garg@gmail.com",
    "amandeepkaur@dtu.ac.in",
    "premprakash@dtu.ac.in",
    "suresh321sharma@gmail.com",
    "opverma@dce.ac.in",
    "sonal.singh0811@gmail.com",
    "wangzom@dtu.ac.in",
    "deepika.kashyap@dtu.ac.in",
    "saurabh.agrawal@dtu.ac.in",
    "sarojbala@dtu.ac.in",
    "nitinpuri2002@yahoo.co.in",
    "snigdhaagrawal@dtu.ac.in",
    "nitindixit@dtu.ac.in",
    "pkjain@dce.ac.in",
    "versha.sehgal@dtu.ac.in",
    "priyamahajan@dtu.ac.in",
    "kanup@dtu.ac.in",
    "virender@dtu.ac.in",
    "ravijadon@dtu.ac.in",
    "mukshi87@gmail.com",
    "ravimed@dtu.ac.in",
    "anushrutivagrani@dtu.ac.in",
    "bharatbajaj@dtu.ac.in",
    "kumarpraveen@dtu.ac.in",
    "stnagarajan@dce.ac.in",
    "rambhagat@dce.ac.in",
    "sri_richa@rediffmail.com",
    "jaysingh@dtu.ac.in",
    "rajeevkumar@dtu.ac.in",
    "anuragchauhan@dtu.ac.in",
    "prakashchandra@dtu.ac.in",
    "rsrivastava@dce.ac.in",
    "rahulkatarya@dtu.ac.in",
    "anandkumar@dtu.ac.in",
    "abhishek@dtu.ac.in",
    "hctaneja@rediffmail.com",
    "manjukmys@gmail.com",
    "arkongan@dce.ac.in",
    "sahuanilkr@yahoo.co.in",
    "vinodsingh@dtu.ac.in",
    "umanangia@dce.ac.in",
    "narendra.kumar@dtu.ac.in",
    "vipin@dce.ac.in",
    "manojsethi@dce.ac.in",
    "Vivekkumar.ag@gmail.com",
    "anubhamandal@dce.ac.in",
    "mayankkumar@dtu.ac.in",
    "ankitatehlan@dtu.ac.in",
    "prof_sureshsharma@dtu.ac.in",
    "shwetameena@dtu.ac.in",
    "joshidheeraj@dce.ac.in",
    "rahulthakur@dtu.ac.in",
    "sudarshan_valluru@dce.ac.in",
    "sudhirwarkar@gmail.com",
    "nehajain@dtu.ac.in",
    "dr_naokant_deo@yahoo.com",
    "shikhankhera@yahoo.co.in",
    "vpkaushik@kuk.ac.in",
    "srinivaskrovvidi@dtu.ac.in",
    "dinesh_chutani@yahoo.com",
    "bhavneshjaint@dtu.ac.in",
    "akgupta@dtu.ac.in",
    "Rathi.nilam@gmail.com",
    "rbirok@gmail.com",
    "lucky.krishnia@gmail.com",
    "mukhtiarsingh@dce.ac.in",
    "anil.kumar@cy.iitr.ac.in",
    "archanarani@dce.ac.in",
    "rajanyadav@dtu.ac.in",
    "pksuri@dtu.ac.in",
    "ramankumar@dtu.ac.in",
    "drbhaskhar@dtu.ac.in",
    "lndas@dce.ac.in",
    "rohitkumar@dtu.ac.in",
    "priyajain2000@rediffmail.com",
    "cmp.npl@gmail.com",
    "kritisuneja@dtu.ac.in",
    "nsraghava@dtu.ac.in",
    "deenan.santhiya@gmail.com",
    "rkyadav@dtu.ac.in",
    "divyamishra@dtu.ac.in",
    "parthapratimdas@dtu.ac.in",
    "rajendraprasad@dtu.ac.in",
    "nkjain@dtu.ac.in",
    "satyajitsahu@dtu.ac.in",
    "jasrajmeena@dtu.ac.in",
    "s.indu@dce.ac.in",
    "sucheta.sardar@dtu.ac.in",
    "gulistaan@dtu.ac.in",
    "rituagarwal@dtu.ac.in",
    "rakeshshankar@dtu.ac.in",
    "amitpal@dce.ac.in",
    "himanshusingh@dtu.ac.in",
    "vishwakamal@dce.ac.in",
    "sumedhaseniaray@dtu.ac.in",
    "sandeepkumar@dtu.ac.in",
    "akshay.mool@dtu.ac.in",
    "mamtarani@dtu.ac.in",
    "krishna@dtu.ac.in",
    "rajkumarsingh@dce.ac.in",
    "sanjayb@dtu.ac.in",
    "saritabaghel@dtu.ac.in",
    "ferro_2005_sam@yahoo.co.in",
    "ajeetdph@gmail.com",
    "navneetab@dce.ac.in",
    "agrawals.iit@gmail.com",
    "manishkumar@dtu.ac.in",
    "rammurtiieju05@gmail.com",
    "yashahasija@dtu.ac.in",
    "kusumlata@dtu.ac.in",
    "rajivchaudhary@dce.ac.in",
    "jagvinder.singh@dtu.ac.in",
    "anurag.chaturvedi@dtu.ac.in",
    "rahulbaghel@dtu.ac.in",
    "jnrai@dce.ac.in",
    "dr.rajeshmits@gmail.com",
    "saurabh.dtu@gmail.com",
    "nipunbansal@dtu.ac.in",
    "singh_dr_ram@yahoo.com",
    "smaji@dce.ac.in",
    "ankursharma@dtu.ac.in",
    "atulkumaragarwal@dce.ac.in",
    "lokeshgautam21@gmail.com",
    "sahil.bhukal@dtu.ac.in",
    "dcmeena@dce.ac.in",
    "verma15.monika@gmail.com",
    "spkumar@dce.ac.in",
    "paraskumar@dtu.ac.in",
    "darshankalasua@dtu.ac.in",
    "shatakshi18jha@gmail.com",
    "moirangthembikensingh@dtu.ac.in",
    "saurabhcsaxena@dtu.ac.in",
    "binduverma@dtu.ac.in",
    "satyabrata@dtu.ac.in",
    "naval.garg@dtu.ac.in",
    "pravirkumar@dtu.ac.in",
    "sumit.singh@dtu.ac.in",
    "pankajdahiya@dtu.ac.in",
    "dipayandas@dtu.ac.in",
    "sumitkale785@gmail.com",
    "divyashikha@dtu.ac.in",
    "bjhamnani@gmail.com",
    "vnykmr7@gmail.com",
    "cpsphd@rediffmail.com",
    "rajeevmishraiitr@gmail.com",
    "richasharma@dtu.ac.in",
    "anilkumar76@dtu.ac.in",
    "bansi.malhotra@gmail.com",
    "geetanjali.getz@gmail.com",
    "sachindhariwal@dtu.ac.in",
    "neerajrathi@dtu.ac.in",
    "vishalverma@dce.ac.in",
    "hctaneja@dce.ac.in",
    "shivaniyadav@dtu.ac.in",
    "rajivkapoor@dce.ac.in",
    "dineshkumar@dtu.ac.in",
    "parihar.anil@gmail.com",
    "ssingh.pk@gmail.com",
    "goonjanjain@dtu.ac.in",
    "sanbukumar@dce.ac.in",
    "msmehata@dtu.ac.in",
    "yogendra.meena@dtu.ac.in",
    "akshay.mann@dtu.ac.in",
    "sanjayyadav@dtu.ac.in",
    "prateeksaini@dtu.ac.in",
    "dineshudar@dtu.ac.in",
    "aksingh@dce.ac.in",
    "rajesh@dce.ac.in",
    "rajeshkumar@dtu.ac.in",
    "suman.bhowmick@dce.ac.in",
    "skgarg@dce.ac.in",
    "geetanjali.garg@dtu.ac.in",
    "a.b.bhattacharya@dtu.ac.in",
    "reetawattal@dce.ac.in",
    "amit@dtu.ac.in",
    "ashishkulkarni@dtu.ac.in",
    "awadheshg@gmail.com",
    "ankityadav@dtu.ac.in",
    "vijaygautam@dce.ac.in",
    "lkdas@dtu.ac.in",
    "anshulujlayan@dtu.ac.in",
    "skdas4321@rediffmail.com",
    "bhanumurthykv@yahoo.com",
    "harleenkaur@dtu.ac.in",
    "rakesh1653@gmail.com",
    "rshahacno@yahoo.com",
    "rohitbeniwal@dtu.ac.in",
    "rahul_gupta@dtu.ac.in",
    "sandeep.kumar@dtu.ac.in",
    "dsnagesh@dce.edu",
    "rachnagarg@dce.ac.in",
    "akgupta@dce.ac.in",
    "sukuyd@gmail.com",
    "pawansingh@dtu.ac.in",
    "minnijain@dtu.ac.in",
    "nitinkumarpuri@dtu.ac.in",
    "roli.purwar@gmail.com",
    "ASHISH@DTU.AC.IN",
    "poonam@dtu.ac.in",
    "pramavishnoi@dtu.ac.in",
    "ritikachopra@dtu.ac.in",
    "rishuchaujar@rediffmail.com",
    "veenushankar@dtu.ac.in",
    "ratnes123@gmail.com",
    "kapil@ieee.org",
    "sumit.khandelwal@dtu.ac.in",
    "nmprasad@dce.ac.in",
    "samsher@dce.ac.in",
    "rohit.kumar@dtu.ac.in",
    "mzunaid@dtu.ac.in",
    "pvramkumar@dce.ac.in",
    "nirendradev@dce.ac.in",
    "saurabhmishra@dtu.ac.in",
    "kapil.kumar@dtu.ac.in",
    "dryogitakalra@gmail.com",
    "puneet.arora@dtu.ac.in",
    "rohan92@dtu.ac.in",
    "seemasingh@dce.ac.in",
    "meenarl@dtu.ac.in",
    "aroraankita@dtu.ac.in",
    "nidhimaheshwari@dtu.ac.in",
    "rcsingh@dce.ac.in",
    "dkumar@dce.ac.in",
    "hksingh@dtu.ac.in",
    "anilsingh@dtu.ac.in",
    "nandkumar@dce.ac.in",
    "vinod_k@dtu.ac.in",
    "archanasingh@dtu.ac.in",
    "anil@dtu.ac.in",
    "neeraj.sharma@dtu.ac.in",
    "rkg67ap@yahoo.com",
    "ashokmadan@dce.ac.in",
    "korsudipta@rediffmail.com",
    "madhusudan@dce.ac.in",
    "brgrobert@dce.ac.in",
    "ashutoshpandey@dtu.ac.in",
    "nand.dce@gmail.com",
    "akgupta@dce.edu",
    "msc_1976@yahoo.com",
    "kashishkumar@dtu.ac.in",
    "bbarora@dce.ac.in",
    "simranbhullar@dtu.ac.in",
    "brijkishore.tyagi@gmail.com",
    "bansi.malhotra@dce.ac.in",
    "prashant.shambharkar@dtu.ac.in",
    "sanjay.kumar@dtu.ac.in",
    "chhavi.dhiman@dtu.ac.in",
    "prmeena@dtu.ac.in",
    "ranganath@dce.ac.in",
    "sharmajaigopal@gmail.com",
    "sanjaypatidar@dtu.ac.in",
    "akhilesharora@dce.ac.in",
    "piyushtewari@dtu.ac.in",
    "rajesh.sharma@dtu.ac.in",
    "kamalkishor@dce.ac.in",
    "ravi.ud2017@gmail.com",
    "seemasinghdtu@gmail.com",
    "dr_rk_sinha@yahoo.com",
    "hbbohidar@jnu.ac.in",
    "bjhamnani@dce.ac.in",
    "maansi.gupta@dtu.ac.in",
    "amookerjee@dtu.ac.in",
    "dgupta@dce.ac.in",
    "gurjitkaur@dtu.ac.in",
    "hariom.jorwal@dtu.ac.in",
    "anjanagupta@dce.ac.in",
    "sharmajaigopal@dce.ac.in",
    "pallavi.kalra@dtu.ac.in",
    "bhartisingh@dtu.ac.in",
    "garimasolanki@dtu.ac.in",
    "avinashratre@dtu.ac.in",
    "prakashchittora@dtu.ac.in",
    "abhishek.kumar@dtu.ac.in",
    "kaustubh@dtu.ac.in",
    "rsreejeth@dtu.ac.in",
    "rakeshkumar@dce.ac.in",
    "ruchikamalhotra@dtu.ac.in",
    "seemasinghdce@yahoo.com",
    "dvishwakarma@gmail.com",
    "narendrakumar@dtu.ac.in",
    "rewarisonam@gmail.com",
    "raminderkaur@dce.ac.in",
    "nareshkumar@dce.ac.in",
    "dinesh@dtu.ac.in",
    "yuvraj@dce.ac.in",
    "sharafunisa@dtu.ac.in",
    "kapilchaudhri@dtu.ac.in",
    "ravigpt0709@gmail.com",
    "rituraj.ahirwar@gmail.com",
    "priyankameel@dtu.ac.in",
    "varsha@dtu.ac.in",
    "gpawadhiya@dce.ac.in",
    "seba_406@yahoo.in",
    "mkg1109@rediffmail.com",
    "gcmaheshwari2004@yahoo.com",
    "shally.gupta@dtu.ac.in",
    "deeptiaggrawal@dtu.ac.in",
    "abhinavchaudhary@dtu.ac.in",
    "aksrivastava@dce.ac.in",
    "alokverma@dce.ac.in",
    "anantbhardwaj@dtu.ac.in",
    "anupama@dtu.ac.in",
    "sakshikukreja@dtu.ac.in",
    "rinkusharmagtbit@gmail.com",
    "rajiv.arora@nic.in"
  ],
  "all_phones": [],
  "statistics": {
    "professors_with_email": 381,
    "professors_with_phone": 0
  }
}